pyautogui/__init__.py
pyautogui/__main__.py
pyautogui/_pyautogui_java.py
pyautogui/_pyautogui_osx.py
pyautogui/_pyautogui_win.py
pyautogui/_pyautogui_x11.py
PyAutoGUI_Soraban-0.9.56.dist-info/AUTHORS.txt
PyAutoGUI_Soraban-0.9.56.dist-info/LICENSE.txt
PyAutoGUI_Soraban-0.9.56.dist-info/METADATA
PyAutoGUI_Soraban-0.9.56.dist-info/WHEEL
PyAutoGUI_Soraban-0.9.56.dist-info/top_level.txt
PyAutoGUI_Soraban-0.9.56.dist-info/RECORD
