Metadata-Version: 2.1
Name: PyAutoGUI-Soraban
Version: 0.9.56
Summary: PyAutoGUI lets Python control the mouse and keyboard, and other GUI automation tasks. For Windows, macOS, and Linux, on Python 3 and 2.
Home-page: https://github.com/asweigart/pyautogui
Author: Al Sweigart
Author-email: al@inventwithpython.com
License: BSD
Keywords: gui automation test testing keyboard mouse cursor click press keystroke control
Classifier: Development Status :: 4 - Beta
Classifier: Environment :: Win32 (MS Windows)
Classifier: Environment :: X11 Applications
Classifier: Environment :: MacOS X
Classifier: Intended Audience :: Developers
Classifier: License :: OSI Approved :: BSD License
Classifier: Operating System :: OS Independent
Classifier: Programming Language :: Python
Classifier: Programming Language :: Python :: 3
Classifier: Programming Language :: Python :: 3.1
Classifier: Programming Language :: Python :: 3.2
Classifier: Programming Language :: Python :: 3.3
Classifier: Programming Language :: Python :: 3.4
Classifier: Programming Language :: Python :: 3.5
Classifier: Programming Language :: Python :: 3.6
Classifier: Programming Language :: Python :: 3.7
Classifier: Programming Language :: Python :: 3.8
Classifier: Programming Language :: Python :: 3.9
Classifier: Programming Language :: Python :: 3.10
Classifier: Programming Language :: Python :: 3.11
License-File: LICENSE.txt
License-File: AUTHORS.txt
Requires-Dist: pymsgbox
Requires-Dist: pytweening (>=1.0.4)
Requires-Dist: pyscreeze (>=0.1.21)
Requires-Dist: pygetwindow (>=0.0.5)
Requires-Dist: mouseinfo
Requires-Dist: pyobjc-core ; platform_system == "Darwin"
Requires-Dist: pyobjc-framework-quartz ; platform_system == "Darwin"
Requires-Dist: python-xlib ; platform_system == "Linux" and python_version < "3.0"
Requires-Dist: python3-Xlib ; platform_system == "Linux" and python_version >= "3.0"
